stax_module_sdk/Stax.py
stax_module_sdk/__init__.py
stax_module_sdk/helpers.py
stax_module_sdk/pytext.py
stax_module_sdk/wrapper.py
stax_ta_automation_sdk-0.2.0.data/scripts/stax_module_cli
stax_ta_automation_sdk-0.2.0.dist-info/METADATA
stax_ta_automation_sdk-0.2.0.dist-info/WHEEL
stax_ta_automation_sdk-0.2.0.dist-info/top_level.txt
stax_ta_automation_sdk-0.2.0.dist-info/RECORD
