Metadata-Version: 2.4
Name: stax_ta_automation_sdk
Version: 0.2.0
Summary: Stax.ai Module SDK
Home-page: https://bitbucket.org/staxai/stax-module-sdk-py
Author: Stax.ai, Inc. <https://stax.ai>
Author-email: naru@stax.ai
License: CC-BY-NC 4.0
Classifier: Programming Language :: Python :: 3
Classifier: Operating System :: OS Independent
Requires-Python: >=3.6
Requires-Dist: retry_requests
Dynamic: author
Dynamic: author-email
Dynamic: classifier
Dynamic: description
Dynamic: description-content-type
Dynamic: home-page
Dynamic: license
Dynamic: requires-dist
Dynamic: requires-python
Dynamic: summary
